Metadata-Version: 2.1
Name: deploy-it
Version: 0.3.3
Summary: Deploy Django projects to virtual private server in a single command.
Home-page: https://github.com/meticulousCraftman/deploy_it
Author: Apoorva Singh
Author-email: apoorva.singh157@gmail.com
License: MIT
Keywords: python devops django gunicorn nginx
Platform: UNKNOWN
Classifier: Programming Language :: Python :: 3
Classifier: License :: OSI Approved :: MIT License
Classifier: Operating System :: OS Independent
Requires-Python: >=3.6
